models_package/__init__.py
models_package/models/__init__.py
models_package/models/booking.py
models_package/models/flight.py
models_package/models/notification.py
models_package/models/user.py
django_models_package-1.2.dist-info/METADATA
django_models_package-1.2.dist-info/WHEEL
django_models_package-1.2.dist-info/top_level.txt
django_models_package-1.2.dist-info/RECORD
