Metadata-Version: 2.1
Name: django-models-package
Version: 1.2
Summary: A reusable Django models package
Home-page: https://github.com/yourusername/django-models-package
Author: Sayrex
Author-email: reshetneff2013@gmail.com
Classifier: Programming Language :: Python :: 3
Classifier: Framework :: Django
Classifier: License :: OSI Approved :: MIT License
Classifier: Operating System :: OS Independent
Requires-Dist: Django >=3.0
